Team_1_library/__init__.py
Team_1_library/functions.py
Team_1_library-1.1.dist-info/LICENSE.md
Team_1_library-1.1.dist-info/METADATA
Team_1_library-1.1.dist-info/WHEEL
Team_1_library-1.1.dist-info/top_level.txt
Team_1_library-1.1.dist-info/RECORD
