Metadata-Version: 2.2
Name: Team_1_library
Version: 1.1
Summary: Data prerpocess library with missing value imputation and outlier correction functions.
Home-page: https://github.com/Manex14/Team_1_library
Author: Jokin Agirre, Irene Alvarez, Uxue Auzmendi, Jon Lorenzo, Manex Ugarte 
Author-email: manex.ugarte@alumni.mondragon.edu
Classifier: Programming Language :: Python :: 3
Classifier: License :: OSI Approved :: MIT License
Classifier: Operating System :: OS Independent
Requires-Python: >=3.8
License-File: LICENSE.md
Requires-Dist: pandas
Requires-Dist: scipy
Requires-Dist: numpy
Requires-Dist: scikit-learn
Requires-Dist: fuzzywuzzy
Dynamic: author
Dynamic: author-email
Dynamic: classifier
Dynamic: description
Dynamic: description-content-type
Dynamic: home-page
Dynamic: requires-dist
Dynamic: requires-python
Dynamic: summary
